SparkMLTransforms/__init__.py
SparkMLTransforms/aggregation.py
SparkMLTransforms/base.py
SparkMLTransforms/encoder.py
SparkMLTransforms/event.py
SparkMLTransforms/feature.py
SparkMLTransforms/lagged.py
SparkMLTransforms/seasonality.py
SparkMLTransforms/utils.py
SparkMLTransforms/version.py
SparkMLTransforms-0.0.5.dist-info/LICENSE
SparkMLTransforms-0.0.5.dist-info/METADATA
SparkMLTransforms-0.0.5.dist-info/WHEEL
SparkMLTransforms-0.0.5.dist-info/top_level.txt
SparkMLTransforms-0.0.5.dist-info/RECORD
