Metadata-Version: 2.1
Name: SparkMLTransforms
Version: 0.0.5
Summary: Transformations in Spark for ML Features
Home-page: https://https://github.com/tianle91/spark-ml-transforms
Author: Tianle Chen
Author-email: tianlechen@gmail.com
Classifier: Programming Language :: Python :: 3
Classifier: License :: OSI Approved :: MIT License
Classifier: Operating System :: OS Independent
Requires-Python: >=3.7
License-File: LICENSE
Requires-Dist: pyspark (>=3.2)
Requires-Dist: pandas (>=1.5)
Requires-Dist: SpaceTimePandas (>=0.3.3)
Requires-Dist: xgboost (>=1.7)
